pyrdms/__init__.py
pyrdms/__main__.py
pyrdms/app.py
pyrdms/client/__init__.py
pyrdms/controllers/__init__.py
pyrdms/controllers/mappers.py
pyrdms/controllers/rdms.py
pyrdms/controllers/test_mappers.py
pyrdms/core/__init__.py
pyrdms/core/entities.py
pyrdms/core/services.py
pyrdms/exceptions.py
pyrdms/proto/__init__.py
pyrdms/proto/rdm_pb2.py
pyrdms/proto/rdm_pb2.pyi
pyrdms/proto/rdm_pb2_grpc.py
pyrdms/repo/__init__.py
pyrdms/repo/decorators.py
pyrdms/repo/local.py
pyrdms/repo/test_local.py
pyrdms/repo/util.py
pyrdms-0.2.0.dist-info/METADATA
pyrdms-0.2.0.dist-info/WHEEL
pyrdms-0.2.0.dist-info/RECORD
