Metadata-Version: 2.1
Name: pyrdms
Version: 0.2.0
Summary: Python remote domain model server for d0sl core
Author: Andrey Gumirov
Author-email: andreyt45@gmail.com
Requires-Python: >=3.10,<4.0
Classifier: Programming Language :: Python :: 3
Classifier: Programming Language :: Python :: 3.10
Classifier: Programming Language :: Python :: 3.11
Classifier: Programming Language :: Python :: 3.12
Requires-Dist: grpcio (>=1.62.1,<2.0.0)
Requires-Dist: protobuf (>=5.26.1,<6.0.0)
